README.md
setup.py
agileutil/__init__.py
agileutil/cache_wrap.py
agileutil/compress.py
agileutil/consul.py
agileutil/db.py
agileutil/eventloop.py
agileutil/log.py
agileutil/orm.py
agileutil/table_writer.py
agileutil/util.py
agileutil/wrap.py
agileutil.egg-info/PKG-INFO
agileutil.egg-info/SOURCES.txt
agileutil.egg-info/dependency_links.txt
agileutil.egg-info/entry_points.txt
agileutil.egg-info/requires.txt
agileutil.egg-info/top_level.txt
agileutil/algorithm/__init__.py
agileutil/algorithm/bloomfilter.py
agileutil/algorithm/hashtable.py
agileutil/algorithm/lru.py
agileutil/cli/__init__.py
agileutil/cli/cli.py
agileutil/cli/entry.py
agileutil/http/__init__.py
agileutil/http/factory.py
agileutil/http/request.py
agileutil/http/response.py
agileutil/http/router.py
agileutil/http/server.py
agileutil/http/status.py
agileutil/http/transport.py
agileutil/rpc/__init__.py
agileutil/rpc/client.py
agileutil/rpc/compress.py
agileutil/rpc/const.py
agileutil/rpc/discovery.py
agileutil/rpc/encrypt.py
agileutil/rpc/exception.py
agileutil/rpc/method.py
agileutil/rpc/protocal.py
agileutil/rpc/serialize.py
agileutil/rpc/server.py
agileutil/rpc/transport.py