Metadata-Version: 1.1
Name: agileutil
Version: 0.0.26
Summary: Light, simple, asynchronous RPC framework for Python
Home-page: UNKNOWN
Author: tank
Author-email: UNKNOWN
License: MIT
Keywords: agileutil
Platform: any
Classifier: Programming Language :: Python :: 3.6
Classifier: Programming Language :: Python :: 3.7
Classifier: Programming Language :: Python :: 3.8
Classifier: Programming Language :: Python :: 3.9
